fl_pkg/EventsManager.py
fl_pkg/ServerConcHandler.py
fl_pkg/__init__.py
fl_pkg/client_process.py
fl_pkg/event_service_pb2.py
fl_pkg/event_service_pb2.pyi
fl_pkg/event_service_pb2_grpc.py
fl_pkg/federation_pb2.py
fl_pkg/federation_pb2.pyi
fl_pkg/federation_pb2_grpc.py
fl_pkg/server_process.py
fl_pkg/models/CNNModel.py
fl_pkg/models/FCNNModel.py
fl_pkg/models/LLRModel.py
fl_pkg/models/XGBModel.py
fl_pkg/models/__init__.py
fl_pkg/server_aggregators/CNNAgg.py
fl_pkg/server_aggregators/FCNNAgg.py
fl_pkg/server_aggregators/LLRAgg.py
fl_pkg/server_aggregators/XGBAgg.py
fl_pkg/server_aggregators/__init__.py
fl_pkg/support/__init__.py
fl_pkg/support/api_caller.py
fl_pkg/support/data_reader_compact.py
fl_pkg/support/dataloader.py
fl_pkg/support/parameter.py
fl_pkg/support/utils.py
fl_pkg-0.3.0.dist-info/licenses/LICENSE
fl_pkg-0.3.0.dist-info/METADATA
fl_pkg-0.3.0.dist-info/WHEEL
fl_pkg-0.3.0.dist-info/top_level.txt
fl_pkg-0.3.0.dist-info/RECORD
