Metadata-Version: 2.4
Name: fl_pkg
Version: 0.3.0
Summary: A short description
Author-email: Nicola <nicolahu1997@gmail.com>
Classifier: Programming Language :: Python :: 3
Classifier: License :: OSI Approved :: MIT License
Requires-Python: >=3.10
License-File: LICENSE
Requires-Dist: grpcio==1.70.0
Dynamic: license-file
